[
  {
    "text": "are all ASOS products vegan?",
    "intent": "faq_fur",
    "intent_prediction": {
      "name": "faq_animal_welfare",
      "confidence": 0.9982455372810364
    }
  },
  {
    "text": "do you use vegan fur?",
    "intent": "faq_fur",
    "intent_prediction": {
      "name": "faq_animal_welfare",
      "confidence": 0.9979243278503418
    }
  },
  {
    "text": "I am going on holiday and want my order delivered to my hotel",
    "intent": "faq_delivery_address",
    "intent_prediction": {
      "name": "faq_delivery_slot",
      "confidence": 0.39807191491127014
    }
  },
  {
    "text": "I would like to change my order to a different item",
    "intent": "faq_exchange_item",
    "intent_prediction": {
      "name": "faq_missing_item",
      "confidence": 0.13998942077159882
    }
  },
  {
    "text": "How do I find out where my order is?",
    "intent": "faq_track_delivery",
    "intent_prediction": {
      "name": "faq_missing_item",
      "confidence": 0.9662241339683533
    }
  },
  {
    "text": "How can I be sure that the cotton I buy is ethically sourced?",
    "intent": "faq_responsible_shopping",
    "intent_prediction": {
      "name": "faq_animal_welfare",
      "confidence": 0.35180431604385376
    }
  },
  {
    "text": "It has been more than 14 days since I made a return",
    "intent": "faq_return_received",
    "intent_prediction": {
      "name": "faq_account_sign_in",
      "confidence": 0.2654842138290405
    }
  },
  {
    "text": "how do i log in to my account",
    "intent": "faq_account_sign_in",
    "intent_prediction": {
      "name": "faq_change_password",
      "confidence": 0.988670289516449
    }
  },
  {
    "text": "How to unlock your account",
    "intent": "faq_account_sign_in",
    "intent_prediction": {
      "name": "faq_change_password",
      "confidence": 0.8048313856124878
    }
  },
  {
    "text": "My order wasn't delivered, whats going on?",
    "intent": "faq_missing_item",
    "intent_prediction": {
      "name": "faq_order_not_received",
      "confidence": 0.6598550081253052
    }
  },
  {
    "text": "My jeans ripped after 3 washes",
    "intent": "faq_faulty_item",
    "intent_prediction": {
      "name": "faq_missing_item",
      "confidence": 0.26515281200408936
    }
  },
  {
    "text": "The zip on my jeans is faulty",
    "intent": "faq_faulty_item",
    "intent_prediction": {
      "name": "faq_missing_item",
      "confidence": 0.32637232542037964
    }
  },
  {
    "text": "Are you cruelty-free?",
    "intent": "faq_animal_welfare",
    "intent_prediction": {
      "name": "faq_fur",
      "confidence": 0.4730399250984192
    }
  },
  {
    "text": "What if I have a question about my order?",
    "intent": "faq_returns_policy",
    "intent_prediction": {
      "name": "faq_order_not_received",
      "confidence": 0.555206298828125
    }
  }
]