[
  {
    "text": "I was sent the wrong item how can I have it delivered to another address?",
    "intent": "faq_delivery_address",
    "intent_prediction": {
      "name": "faq_wrong_item_received",
      "confidence": 0.9631388187408447
    }
  },
  {
    "text": "How do I know if my purchase has been shipped?",
    "intent": "faq_track_delivery",
    "intent_prediction": {
      "name": "faq_order_not_received",
      "confidence": 0.9486486911773682
    }
  },
  {
    "text": "What are ASOS doing to tackle the issue of fast fashion?",
    "intent": "faq_responsible_shopping",
    "intent_prediction": {
      "name": "faq_size_guide",
      "confidence": 0.5835102796554565
    }
  },
  {
    "text": "I've forgotten my password and I can't login into my account?",
    "intent": "faq_account_sign_in",
    "intent_prediction": {
      "name": "faq_change_password",
      "confidence": 0.9879061579704285
    }
  },
  {
    "text": "How to find out where is my order?",
    "intent": "faq_missing_item",
    "intent_prediction": {
      "name": "faq_track_delivery",
      "confidence": 0.9945994019508362
    }
  },
  {
    "text": "My t-shirt is faded",
    "intent": "faq_faulty_item",
    "intent_prediction": {
      "name": "faq_missing_item",
      "confidence": 0.9983454346656799
    }
  },
  {
    "text": "I am waiting for an order but I haven't heard anything from ASOS",
    "intent": "faq_missing_comms",
    "intent_prediction": {
      "name": "faq_order_not_received",
      "confidence": 0.850598931312561
    }
  },
  {
    "text": "ASOS isn't contacting me about my order",
    "intent": "faq_missing_comms",
    "intent_prediction": {
      "name": "faq_returns_policy",
      "confidence": 0.23016533255577087
    }
  },
  {
    "text": "How long do I have the option to return my order?",
    "intent": "faq_returns_policy",
    "intent_prediction": {
      "name": "faq_order_not_received",
      "confidence": 0.22868889570236206
    }
  },
  {
    "text": "I am a size XXL/6XL/14/16/18, what size should I order from ASOS?",
    "intent": "faq_size_guide",
    "intent_prediction": {
      "name": "faq_exchange_item",
      "confidence": 0.5840739011764526
    }
  }
]